websocket_wrapper/__init__.py
websocket_wrapper/client/__init__.py
websocket_wrapper/client/client.py
websocket_wrapper/server/__init__.py
websocket_wrapper/server/client.py
websocket_wrapper/server/protocol.py
websocket_wrapper/server/server.py
websocket_wrapper-0.1.2.dist-info/METADATA
websocket_wrapper-0.1.2.dist-info/WHEEL
websocket_wrapper-0.1.2.dist-info/top_level.txt
websocket_wrapper-0.1.2.dist-info/RECORD
